pvsvg/__init__.py
pvsvg/network.py
pvsvg/scripts/canvas2svg.js
pvsvg/scripts/utils.js
pvsvg/scripts/vis.js
pvsvg/styles/slider.css
pvsvg/styles/vis-network.min.css
pvsvg/templates/template.html
pvsvg-0.1.3.dist-info/LICENSE
pvsvg-0.1.3.dist-info/METADATA
pvsvg-0.1.3.dist-info/WHEEL
pvsvg-0.1.3.dist-info/RECORD
