Metadata-Version: 2.1
Name: pvsvg
Version: 0.1.3
Summary: an implementation of visjs from networkx with export svg
License: MIT
Author: noam teyssier
Author-email: 22600644+noamteyssier@users.noreply.github.com
Requires-Python: >=3.8,<4.0
Classifier: License :: OSI Approved :: MIT License
Classifier: Programming Language :: Python :: 3
Classifier: Programming Language :: Python :: 3.8
Classifier: Programming Language :: Python :: 3.9
Classifier: Programming Language :: Python :: 3.10
Classifier: Programming Language :: Python :: 3.11
Requires-Dist: jinja2 (>=3.1.2,<4.0.0)
Requires-Dist: networkx (>=3.1,<4.0)
